SOP Tabla 1/Tabla1SOP.v

module Tabla1SOP();


reg A, B, C;
wire n1, n2, n3, r1, r2, r3, r4, r5, out;


not na(n1, A);
not nb(n2, B);
not nc(n3, C);
and A1(r1,n1, n2, n3);
and A2(r2,n1, B, n3);
and A3(r3,A, n2, n3);
and A4(r4, A, n2, C);
and A5(r5, A, B, C);
or O1(out, r1, r2, r3, r4, r5);

initial begin
  $display("A B C| Y");
  $display("-------");
  $monitor("%b %b %b | %b", A, B, C, out);
  A = 0; B = 0; C = 0;
  #1 A = 0; B = 0; C = 1;
  #1 A = 0; B = 1; C = 0;
  #1 A = 0; B = 1; C = 1;
  #1 A = 1; B = 0; C = 0;
  #1 A = 1; B = 0; C = 1;
  #1 A = 1; B = 1; C = 0;
  #1 A = 1; B = 1; C = 1;

  #1 $finish;
end

initial
  begin
    $dumpfile("Tabla1SOP_tb.vcd");
    $dumpvars(0, Tabla1SOP);
  end

endmodule

SOP Tabla 1/Tabla1SOP_tb.vcd
$date
	Sun Aug 02 02:34:42 2020
$end
$version
	Icarus Verilog
$end
$timescale
	1ps
$end
$scope module Tabla1SOP $end
$var wire 1 ! n1 $end
$var wire 1 " n2 $end
$var wire 1 # n3 $end
$var wire 1 $ out $end
$var wire 1 % r1 $end
$var wire 1 & r2 $end
$var wire 1 ' r3 $end
$var wire 1 ( r4 $end
$var wire 1 ) r5 $end
$var reg 1 * A $end
$var reg 1 + B $end
$var reg 1 , C $end
$upscope $end
$enddefinitions $end
#0
$dumpvars
0,
0+
0*
0)
0(
0'
0&
1%
1$
1#
1"
1!
$end
#1
0$
0%
0#
1,
#2
1$
1&
1#
0"
0,
1+
#3
0$
0&
0#
1,
#4
1$
1'
1#
1"
0!
0,
0+
1*
#5
0'
1(
0#
1,
#6
0$
0(
1#
0"
0,
1+
#7
1$
1)
0#
1,
