SOP Tabla 3/Tabla3SOP.v

module Tabla3SOP();


reg A, B, C, D;
wire n1, n2, n3, n4, r1, r2, r3, r4, r5, r6, r7, out;


not na(n1, A);
not nb(n2, B);
not nc(n3, C);
not nd(n4, D);
and A1(r1, n1, n2, n3, n4);
and A2(r2, n1, n2, n3, D);
and A3(r3, n1, n2, C, n4);
and A4(r4, n1, n2, C, D);
and A5(r5, A, n2, n3, n4);
and A6(r6, A, n2, C, n4);
and A7(r7, A, B, C, n4);
or O1(out, r1, r2, r3, r4, r5, r6, r7);

initial begin
  $display("A B C| Y");
  $display("-------");
  $monitor("%b %b %b %b | %b", A, B, C, D, out);
  A = 0; B = 0; C = 0; D = 0;
  #1 A = 0; B = 0; C = 0; D = 1;
  #1 A = 0; B = 0; C = 1; D = 0;
  #1 A = 0; B = 0; C = 1; D = 1;
  #1 A = 0; B = 1; C = 0; D = 0;
  #1 A = 0; B = 1; C = 0; D = 1;
  #1 A = 0; B = 1; C = 1; D = 0;
  #1 A = 0; B = 1; C = 1; D = 1;
  #1 A = 1; B = 0; C = 0; D = 0;
  #1 A = 1; B = 0; C = 0; D = 1;
  #1 A = 1; B = 0; C = 1; D = 0;
  #1 A = 1; B = 0; C = 1; D = 1;
  #1 A = 1; B = 1; C = 0; D = 0;
  #1 A = 1; B = 1; C = 0; D = 1;
  #1 A = 1; B = 1; C = 1; D = 0;
  #1 A = 1; B = 1; C = 1; D = 1;
  #1 $finish;
end

initial
  begin
    $dumpfile("Tabla3SOP_tb.vcd");
    $dumpvars(0, Tabla3SOP);
  end

endmodule

SOP Tabla 3/Tabla3SOP_tb.vcd
$date
	Sun Aug 02 03:13:42 2020
$end
$version
	Icarus Verilog
$end
$timescale
	1ps
$end
$scope module Tabla3SOP $end
$var wire 1 ! n1 $end
$var wire 1 " n2 $end
$var wire 1 # n3 $end
$var wire 1 $ n4 $end
$var wire 1 % out $end
$var wire 1 & r1 $end
$var wire 1 ' r2 $end
$var wire 1 ( r3 $end
$var wire 1 ) r4 $end
$var wire 1 * r5 $end
$var wire 1 + r6 $end
$var wire 1 , r7 $end
$var reg 1 - A $end
$var reg 1 . B $end
$var reg 1 / C $end
$var reg 1 0 D $end
$upscope $end
$enddefinitions $end
#0
$dumpvars
00
0/
0.
0-
0,
0+
0*
0)
0(
0'
1&
1%
1$
1#
1"
1!
$end
#1
0&
1'
0$
10
#2
1(
0'
1$
0#
00
1/
#3
0(
1)
0$
10
#4
0%
1$
0)
1#
0"
00
0/
1.
#5
0$
10
#6
1$
0#
00
1/
#7
0$
10
#8
1%
1*
1$
1#
1"
0!
00
0/
0.
1-
#9
0%
0*
0$
10
#10
1%
1+
1$
0#
00
1/
#11
0%
0+
0$
10
#12
1$
1#
0"
00
0/
1.
#13
0$
10
#14
1%
1,
1$
0#
00
1/
#15
0%
0,
0$
10
