POS Tabla 1/Tabla1POS.v

module Tabla1POS();


reg A, B, C;
wire n1, n2, n3, o1, o2, o3, out;


not na(n1, A);
not nb(n2, B);
not nc(n3, C);
or oa(o1, A, B, n3);
or ob(o2, A, n2, n3);
or oc(o3, n1, n2, C);
and an(out, o1, o2, o3);

initial begin
  $display("A B C| Y");
  $display("-------");
  $monitor("%b %b %b | %b", A, B, C, out);
  A = 0; B = 0; C = 0;
  #1 A = 0; B = 0; C = 1;
  #1 A = 0; B = 1; C = 0;
  #1 A = 0; B = 1; C = 1;
  #1 A = 1; B = 0; C = 0;
  #1 A = 1; B = 0; C = 1;
  #1 A = 1; B = 1; C = 0;
  #1 A = 1; B = 1; C = 1;

  #1 $finish;
end

initial
  begin
    $dumpfile("Tabla1POS_tb.vcd");
    $dumpvars(0, Tabla1POS);
  end

endmodule

POS Tabla 1/Tabla1POS_tb.vcd
$date
	Sun Aug 02 02:10:17 2020
$end
$version
	Icarus Verilog
$end
$timescale
	1ps
$end
$scope module Tabla1POS $end
$var wire 1 ! n1 $end
$var wire 1 " n2 $end
$var wire 1 # n3 $end
$var wire 1 $ o1 $end
$var wire 1 % o2 $end
$var wire 1 & o3 $end
$var wire 1 ' out $end
$var reg 1 ( A $end
$var reg 1 ) B $end
$var reg 1 * C $end
$upscope $end
$enddefinitions $end
#0
$dumpvars
0*
0)
0(
1'
1&
1%
1$
1#
1"
1!
$end
#1
0'
0$
0#
1*
#2
1'
1#
1$
0"
0*
1)
#3
0'
0%
0#
1*
#4
1'
1#
1"
1%
0!
0*
0)
1(
#5
0#
1*
#6
0'
0&
1#
0"
0*
1)
#7
1'
1&
0#
1*
