POS Tabla 3/Tabla3POS.v

module Tabla3POS();


reg A, B, C, D;
wire n1, n2, n3, n4, r1, r2, r3, r4, r5, r6, r7, r8, r9, out;


not na(n1, A);
not nb(n2, B);
not nc(n3, C);
not nd(n4, D);
or A1(r1, A, n2, C, D);
or A2(r2, A, n2, C, n4);
or A3(r3, A, n2, n3, D);
or A4(r4, A, n2, n3, n4);
or A5(r5, n1, B, C, n4);
or A6(r6, n1, B, n3, n4);
or A7(r7, n1, n2, C, D);
or A8(r8, n1, n2, C, n4);
or A9(r9, n1, n2, n3, n4);
and O1(out, r1, r2, r3, r4, r5, r6, r7, r8, r9);

initial begin
  $display("A B C D| Y");
  $display("-------");
  $monitor("%b %b %b %b | %b", A, B, C, D, out);
  A = 0; B = 0; C = 0; D = 0;
  #1 A = 0; B = 0; C = 0; D = 1;
  #1 A = 0; B = 0; C = 1; D = 0;
  #1 A = 0; B = 0; C = 1; D = 1;
  #1 A = 0; B = 1; C = 0; D = 0;
  #1 A = 0; B = 1; C = 0; D = 1;
  #1 A = 0; B = 1; C = 1; D = 0;
  #1 A = 0; B = 1; C = 1; D = 1;
  #1 A = 1; B = 0; C = 0; D = 0;
  #1 A = 1; B = 0; C = 0; D = 1;
  #1 A = 1; B = 0; C = 1; D = 0;
  #1 A = 1; B = 0; C = 1; D = 1;
  #1 A = 1; B = 1; C = 0; D = 0;
  #1 A = 1; B = 1; C = 0; D = 1;
  #1 A = 1; B = 1; C = 1; D = 0;
  #1 A = 1; B = 1; C = 1; D = 1;
  #1 $finish;
end

initial
  begin
    $dumpfile("Tabla3POS_tb.vcd");
    $dumpvars(0, Tabla3POS);
  end

endmodule

POS Tabla 3/Tabla3POS_tb.vcd
$date
	Sun Aug 02 03:25:55 2020
$end
$version
	Icarus Verilog
$end
$timescale
	1ps
$end
$scope module Tabla3POS $end
$var wire 1 ! n1 $end
$var wire 1 " n2 $end
$var wire 1 # n3 $end
$var wire 1 $ n4 $end
$var wire 1 % out $end
$var wire 1 & r1 $end
$var wire 1 ' r2 $end
$var wire 1 ( r3 $end
$var wire 1 ) r4 $end
$var wire 1 * r5 $end
$var wire 1 + r6 $end
$var wire 1 , r7 $end
$var wire 1 - r8 $end
$var wire 1 . r9 $end
$var reg 1 / A $end
$var reg 1 0 B $end
$var reg 1 1 C $end
$var reg 1 2 D $end
$upscope $end
$enddefinitions $end
#0
$dumpvars
02
01
00
0/
1.
1-
1,
1+
1*
1)
1(
1'
1&
1%
1$
1#
1"
1!
$end
#1
0$
12
#2
1$
0#
02
11
#3
0$
12
#4
0%
1$
1'
0&
1#
0"
02
01
10
#5
0'
1&
0$
12
#6
0(
1$
1'
0#
02
11
#7
0)
1(
0$
12
#8
1%
1$
1#
1+
1*
1"
1)
0!
02
01
00
1/
#9
0%
0*
0$
12
#10
1%
1$
1*
0#
02
11
#11
0%
0+
0$
12
#12
1$
1-
0,
1#
1+
0"
02
01
10
#13
0-
1,
0$
12
#14
1%
1$
1-
0#
02
11
#15
0%
0.
0$
12
